{
  "en": {
    "herotext": "Take your car's paint to the next level",
    "herotextparagraph": "In a world of constant innovation, the pursuit of creative solutions becomes a need. In this context, González Car Paint stands out as a leader in automotive aesthetics transformation.",
    "discovermore": "Discover more",
    "bestprizes": "Best prizes",
    "bestprizesmarket": "We have the best prices in the market and various promotions for our customers to take advantage of."
  },
  "es": {
    "herotext": "Lleva la pintura de tu auto al siguiente nivel",
    "herotextparagraph": "En un mundo de constante innovación, la búsqueda de soluciones creativas se convierte en una necesidad. En este contexto, González Car Paint se destaca como líder en la transformación estética automotriz.",
    "discovermore": "Descubre más",
    "bestprizes": "Los mejores precios",
    "bestprizesmarket": "Tenemos los mejores precios del mercado y diferentes promociones para que aprovechen nuestros clientes."
  }
}
